quantjourney_ti/__init__.py
quantjourney_ti/_decorators.py
quantjourney_ti/_errors.py
quantjourney_ti/_indicator_kernels.py
quantjourney_ti/_performance.py
quantjourney_ti/_risk_metrics.py
quantjourney_ti/_streaming.py
quantjourney_ti/_utils.py
quantjourney_ti/indicators.py
quantjourney_ti/technical_indicators.py
quantjourney_ti/_legacy_/technical_indicators.py
quantjourney_ti/kernels/__init__.py
quantjourney_ti/kernels/momentum_numba.py
quantjourney_ti/kernels/trend_numba.py
quantjourney_ti/kernels/volatility_numba.py
quantjourney_ti/kernels/volume_numba.py
quantjourney_ti-0.3.2.dist-info/METADATA
quantjourney_ti-0.3.2.dist-info/WHEEL
quantjourney_ti-0.3.2.dist-info/top_level.txt
quantjourney_ti-0.3.2.dist-info/RECORD
