Metadata-Version: 2.1
Name: quantjourney-ti
Version: 0.3.2
Summary: Comprehensive technical indicators for financial data.
Author-email: Jakub Polec <jakub@quantjourney.pro>
License: MIT License
Project-URL: Homepage, https://quantjourney.substack.com
Project-URL: Repository, https://github.com/QuantJourneyOrg/qj_technical_indicators
Project-URL: Bug Tracker, https://github.com/QuantJourneyOrg/qj_technical_indicators/issues
Keywords: financial,technical analysis,indicators,quant,numba
Classifier: License :: OSI Approved :: MIT License
Classifier: Development Status :: 3 - Alpha
Classifier: Intended Audience :: Developers
Classifier: Intended Audience :: Financial and Insurance Industry
Classifier: Programming Language :: Python :: 3 :: Only
Classifier: Programming Language :: Python :: 3.11
Classifier: Programming Language :: Python :: 3.12
Classifier: Programming Language :: Python :: 3.13
Classifier: Operating System :: OS Independent
Classifier: Topic :: Office/Business :: Financial :: Investment
Classifier: Topic :: Software Development :: Libraries :: Python Modules
Requires-Python: <3.15,>=3.11
Requires-Dist: numpy>=1.26.0
Requires-Dist: pandas<3.0,>=2.0.0
Requires-Dist: numba>=0.59.0
Requires-Dist: scipy<2.0,>=1.11.0
